vga/LFSR.v
module LFSR(
    input clk,           
    input reset,         
    output [3:0] x,      
    output [3:0] y       
);

    reg [3:0] x_reg;     
    reg [3:0] y_reg;    

    wire x_feed, y_feed; // Feedback signals

    // Feedback computation (XOR of selected taps)
    assign x_feed = x_reg[0] ^ x_reg[3]; 
    assign y_feed = y_reg[0] ^ y_reg[3]; 

    // Always block to handle the shift register logic
    always @(posedge clk or posedge reset) begin
        if (reset) begin
            // Initialize the registers to a non-zero value 
            x_reg <= 4'b0011;  // Non-zero initializations
            y_reg <= 4'b1011;  
        end else begin
            // Shift the registers and insert feedback into the LSB
            x_reg <= {x_reg[2:0], x_feed}; // Shift left and insert feedback bit for x
            y_reg <= {y_reg[2:0], y_feed}; // Shift left and insert feedback bit for y
        end
    end

    // Map the outputs to the range 0-9 using modulo operation (0-9)
    assign x = x_reg % 10; 
    assign y = y_reg % 10;

endmodule

vga/LFSR_tb.v
//Testbench for LFSR module --> works!!!
`timescale 1ns/1ps

module LFSR_tb;

    // Declare signals for the testbench
    reg clk;
    reg reset;
    wire [3:0] x;  // 4-bit output for x
    wire [3:0] y;  // 4-bit output for y

    // Instantiate the LFSR module
    LFSR uut (
        .clk(clk),
        .reset(reset),
        .x(x),
        .y(y)
    );

    // Clock generation (50 MHz clock)
    initial clk = 0;
    always #10 clk = ~clk;  // 10 ns period for 50 MHz clock

    // Test sequence
    initial begin
        // Display header
        $display("Time\tReset\tX\tY");
        $monitor("%d\t%b\t%d\t%d", $time, reset, x, y);

        // Initialize signals
        reset = 1;  // Assert reset
        #20;         // Wait for a few clock cycles to propagate reset
        reset = 0;   // Deassert reset
        #500;        // Run simulation for 500 ns

        // End simulation
        $stop;  // Stop the simulation
    end

    // Dump waveform to a VCD file (for visualization in a waveform viewer)
    initial begin
        $dumpfile("LFSR_tb.vcd");
        $dumpvars(0, LFSR_tb);
    end

endmodule

vga/LFSR_tb.vcd
$date
	Sun Nov 24 12:58:00 2024
$end
$version
	Icarus Verilog
$end
$timescale
	1ps
$end
$scope module LFSR_tb $end
$var wire 4 ! y [3:0] $end
$var wire 4 " x [3:0] $end
$var reg 1 # clk $end
$var reg 1 $ reset $end
$scope module uut $end
$var wire 1 # clk $end
$var wire 1 $ reset $end
$var wire 1 % x_feed $end
$var wire 1 & y_feed $end
$var wire 4 ' y [3:0] $end
$var wire 4 ( x [3:0] $end
$var reg 4 ) x_reg [3:0] $end
$var reg 4 * y_reg [3:0] $end
$upscope $end
$upscope $end
$enddefinitions $end
$comment Show the parameter values. $end
$dumpall
$end
#0
$dumpvars
b1011 *
b11 )
b11 (
b1 '
0&
1%
1$
0#
b11 "
b1 !
$end
#10000
1#
#20000
0#
0$
#30000
b110 !
b110 '
b111 "
b111 (
b110 *
b111 )
1#
#40000
0#
#50000
1&
0%
b10 !
b10 '
b101 "
b101 (
b1100 *
b1111 )
1#
#60000
0#
#70000
0&
1%
b1001 !
b1001 '
b100 "
b100 (
b1001 *
b1110 )
1#
#80000
0#
#90000
0%
b10 !
b10 '
b11 "
b11 (
b10 *
b1101 )
1#
#100000
0#
#110000
1%
b100 !
b100 '
b0 "
b0 (
b100 *
b1010 )
1#
#120000
0#
#130000
1&
b1000 !
b1000 '
b101 "
b101 (
b1000 *
b101 )
1#
#140000
0#
#150000
0%
b1 !
b1 '
b1 "
b1 (
b1 *
b1011 )
1#
#160000
0#
#170000
b11 !
b11 '
b110 "
b110 (
b11 *
b110 )
1#
#180000
0#
#190000
1%
b111 !
b111 '
b10 "
b10 (
b111 *
b1100 )
1#
#200000
0#
#210000
0&
0%
b101 !
b101 '
b1001 "
b1001 (
b1111 *
b1001 )
1#
#220000
0#
#230000
1&
b100 !
b100 '
b10 "
b10 (
b1110 *
b10 )
1#
#240000
0#
#250000
0&
b11 !
b11 '
b100 "
b100 (
b1101 *
b100 )
1#
#260000
0#
#270000
1&
1%
b0 !
b0 '
b1000 "
b1000 (
b1010 *
b1000 )
1#
#280000
0#
#290000
b101 !
b101 '
b1 "
b1 (
b101 *
b1 )
1#
#300000
0#
#310000
0&
b1 !
b1 '
b11 "
b11 (
b1011 *
b11 )
1#
#320000
0#
#330000
b110 !
b110 '
b111 "
b111 (
b110 *
b111 )
1#
#340000
0#
#350000
1&
0%
b10 !
b10 '
b101 "
b101 (
b1100 *
b1111 )
1#
#360000
0#
#370000
0&
1%
b1001 !
b1001 '
b100 "
b100 (
b1001 *
b1110 )
1#
#380000
0#
#390000
0%
b10 !
b10 '
b11 "
b11 (
b10 *
b1101 )
1#
#400000
0#
#410000
1%
b100 !
b100 '
b0 "
b0 (
b100 *
b1010 )
1#
#420000
0#
#430000
1&
b1000 !
b1000 '
b101 "
b101 (
b1000 *
b101 )
1#
#440000
0#
#450000
0%
b1 !
b1 '
b1 "
b1 (
b1 *
b1011 )
1#
#460000
0#
#470000
b11 !
b11 '
b110 "
b110 (
b11 *
b110 )
1#
#480000
0#
#490000
1%
b111 !
b111 '
b10 "
b10 (
b111 *
b1100 )
1#
#500000
0#
#510000
0&
0%
b101 !
b101 '
b1001 "
b1001 (
b1111 *
b1001 )
1#
